mseep_openai_websearch_mcp-0.4.4.dist-info/licenses/LICENSE
openai_websearch_mcp/__init__.py
openai_websearch_mcp/__main__.py
openai_websearch_mcp/cli.py
openai_websearch_mcp/server.py
mseep_openai_websearch_mcp-0.4.4.dist-info/METADATA
mseep_openai_websearch_mcp-0.4.4.dist-info/WHEEL
mseep_openai_websearch_mcp-0.4.4.dist-info/entry_points.txt
mseep_openai_websearch_mcp-0.4.4.dist-info/top_level.txt
mseep_openai_websearch_mcp-0.4.4.dist-info/RECORD
