Metadata-Version: 2.4
Name: mseep-openai-websearch-mcp
Version: 0.4.4
Summary: using openai websearch as mcp server
Author-email: mseep <support@skydeck.ai>
Requires-Python: >=3.10
License-File: LICENSE
Requires-Dist: pydantic_extra_types==2.10.3
Requires-Dist: pydantic==2.10.6
Requires-Dist: mcp==1.3.0
Requires-Dist: tzdata==2025.1
Requires-Dist: openai==1.66.2
Requires-Dist: typer==0.15.2
Dynamic: license-file
